CHANGES.txt
MANIFEST.in
README.md
setup.py
src/tinypie/__init__.py
src/tinypie/asmutils.py
src/tinypie/assembler.py
src/tinypie/ast.py
src/tinypie/astviz.py
src/tinypie/bytecode.py
src/tinypie/interpreter.py
src/tinypie/lexer.py
src/tinypie/parser.py
src/tinypie/scope.py
src/tinypie/symbol.py
src/tinypie/tacparser.py
src/tinypie/tokens.py
src/tinypie/vm.py
src/tinypie.egg-info/PKG-INFO
src/tinypie.egg-info/SOURCES.txt
src/tinypie.egg-info/dependency_links.txt
src/tinypie.egg-info/entry_points.txt
src/tinypie.egg-info/not-zip-safe
src/tinypie.egg-info/requires.txt
src/tinypie.egg-info/top_level.txt
src/tinypie/tests/__init__.py
src/tinypie/tests/test_asmlexer.py
src/tinypie/tests/test_assembler.py
src/tinypie/tests/test_astviz.py
src/tinypie/tests/test_interpreter.py
src/tinypie/tests/test_lexer.py
src/tinypie/tests/test_parser.py
src/tinypie/tests/test_vm.py