Metadata-Version: 1.0
Name: tinypie
Version: 0.2
Summary: Tree-Based Interpreter, Compiler and VM for TinyPie language
Home-page: http://github.com/rspivak/tinypie
Author: Ruslan Spivak
Author-email: ruslan.spivak@gmail.com
License: MIT
Platform: UNKNOWN
Classifier: Intended Audience :: Developers
Classifier: License :: OSI Approved :: MIT License
Classifier: Programming Language :: Python
Classifier: Topic :: Software Development :: Interpreters
Classifier: Operating System :: Unix
